CHANGELOG.md
MANIFEST.in
README.md
chew-comparison.ibs0.txt
chew-comparison.mask.txt
chew-comparison.relatedness.txt
requirements.txt
setup.cfg
setup.py
chew/__init__.py
chew/_version.py
chew/cli.py
chew/common.py
chew/compare.py
chew/fingerprint.py
chew/plot_compare.py
chew/plot_var_het.py
chew/roh.py
chew/serve.py
chew/stats.py
chew/data/GRCh37_sites.bed.gz
chew/data/GRCh37_sitesX.bed.gz
chew/data/GRCh38_sites.bed.gz
chew/data/GRCh38_sitesX.bed.gz
ngs_chew.egg-info/PKG-INFO
ngs_chew.egg-info/SOURCES.txt
ngs_chew.egg-info/dependency_links.txt
ngs_chew.egg-info/entry_points.txt
ngs_chew.egg-info/not-zip-safe
ngs_chew.egg-info/requires.txt
ngs_chew.egg-info/top_level.txt
requirements/base.txt
requirements/dev.txt
requirements/misc.txt
requirements/serve.txt
requirements/test.txt
tests/__init__.py
tests/conftest.py
tests/test_compare.py
tests/test_run_fingerprint.py