Metadata-Version: 2.1
Name: ngs-chew
Version: 0.9.2
Summary: NGS Chew
Home-page: https://github.com/bihealth/ngs-chew
Author: Manuel Holtgrewe
Author-email: manuel.holtgrewe@bih-charite.de
License: MIT license
Keywords: bioinformatics
Classifier: Development Status :: 2 - Pre-Alpha
Classifier: Intended Audience :: Developers
Classifier: License :: OSI Approved :: MIT License
Classifier: Natural Language :: English
Classifier: Programming Language :: Python :: 3
Classifier: Programming Language :: Python :: 3.9
Classifier: Programming Language :: Python :: 3.10
Classifier: Programming Language :: Python :: 3.11
Classifier: Programming Language :: Python :: 3.12
Requires-Python: >=3.8
Requires-Dist: logzero
Requires-Dist: tqdm
Requires-Dist: numpy
Requires-Dist: vcfpy
Requires-Dist: pysam
Requires-Dist: pandas
Requires-Dist: plotly
Requires-Dist: scipy
Requires-Dist: click
Requires-Dist: attrs
Requires-Dist: cattrs
Provides-Extra: serve
Requires-Dist: dash; extra == "serve"
Requires-Dist: plotly; extra == "serve"
Requires-Dist: dash-bootstrap-components; extra == "serve"
